capsolver/__init__.py
capsolver/__main__.py
capsolver/api_requestor.py
capsolver/capsolver.py
capsolver/capsolver_object.py
capsolver/check.py
capsolver/error.py
capsolver-1.0.7.dist-info/LICENSE
capsolver-1.0.7.dist-info/LICENSE.rst
capsolver-1.0.7.dist-info/METADATA
capsolver-1.0.7.dist-info/WHEEL
capsolver-1.0.7.dist-info/top_level.txt
capsolver-1.0.7.dist-info/RECORD
