Metadata-Version: 2.1
Name: capsolver
Version: 1.0.7
Summary: capsolver python libary
Home-page: https://github.com/capsolver/capsolver-python
Author: capsolver
Author-email: capsolver.com@gmail.com
Project-URL: Bug Tracker, https://github.com/capsovler/capsovler-python/issues
Classifier: Programming Language :: Python :: 3
Classifier: License :: OSI Approved :: MIT License
Classifier: Operating System :: OS Independent
Requires-Python: >=3.6.8
License-File: LICENSE
License-File: LICENSE.rst
